aigc_comfyui_tools/api/flux_dev_checkpoint.py
aigc_comfyui_tools/api/flux_dev_checkpoint_test.py
aigc_comfyui_tools/api/image_generation.py
aigc_comfyui_tools/api/image_generation_test.py
aigc_comfyui_tools/clis/cli.py
aigc_comfyui_tools/clis/commands/flux_dev_checkpoint.py
aigc_comfyui_tools/clis/commands/image_generation.py
aigc_comfyui_tools/data/jsonfile/flux_dev_checkpoint.json
aigc_comfyui_tools/data/jsonfile/image_generation.json
aigc_comfyui_tools-0.0.3.dist-info/METADATA
aigc_comfyui_tools-0.0.3.dist-info/WHEEL
aigc_comfyui_tools-0.0.3.dist-info/entry_points.txt
aigc_comfyui_tools-0.0.3.dist-info/top_level.txt
aigc_comfyui_tools-0.0.3.dist-info/RECORD
